maptor/__init__.py
maptor/exceptions.py
maptor/input_validation.py
maptor/mtor_types.py
maptor/plot.py
maptor/radau.py
maptor/solution.py
maptor/solution_extraction.py
maptor/solver.py
maptor/summary.py
maptor/summary_benchmark.py
maptor/adaptive/__init__.py
maptor/adaptive/phs/__init__.py
maptor/adaptive/phs/algorithm.py
maptor/adaptive/phs/data_structures.py
maptor/adaptive/phs/error_estimation.py
maptor/adaptive/phs/initial_guess.py
maptor/adaptive/phs/iteration_data.py
maptor/adaptive/phs/numerical.py
maptor/adaptive/phs/refinement.py
maptor/direct_solver/__init__.py
maptor/direct_solver/constraints_solver.py
maptor/direct_solver/core_solver.py
maptor/direct_solver/initial_guess_solver.py
maptor/direct_solver/integrals_solver.py
maptor/direct_solver/types_solver.py
maptor/direct_solver/variables_solver.py
maptor/mechanics/__init__.py
maptor/mechanics/symbolic.py
maptor/mechanics/verification_acrobot.py
maptor/problem/__init__.py
maptor/problem/casadi_build.py
maptor/problem/constraints_problem.py
maptor/problem/core_problem.py
maptor/problem/initial_guess_problem.py
maptor/problem/mesh.py
maptor/problem/solver_interface.py
maptor/problem/state.py
maptor/problem/variables_problem.py
maptor/utils/__init__.py
maptor/utils/constants.py
maptor/utils/coordinates.py
maptor-0.2.1.dist-info/licenses/LICENSE
maptor-0.2.1.dist-info/METADATA
maptor-0.2.1.dist-info/WHEEL
maptor-0.2.1.dist-info/top_level.txt
maptor-0.2.1.dist-info/RECORD
