Metadata-Version: 2.4
Name: maptor
Version: 0.2.1
Summary: Multiphase Adaptive Trajectory Optimizer
Author-email: David Timothy <chendavidtimothy@gmail.com>
Project-URL: Homepage, https://github.com/maptor/maptor
Project-URL: Repository, https://github.com/maptor/maptor
Project-URL: Issues, https://github.com/maptor/maptor/issues
Keywords: control,engineering,optimization,robotics,aerospace,autonomous,trajectory,planning,numerical,simulation
Classifier: Intended Audience :: Science/Research
Classifier: Topic :: Scientific/Engineering :: Mathematics
Classifier: License :: OSI Approved :: GNU Lesser General Public License v3 (LGPLv3)
Classifier: Programming Language :: Python :: 3
Classifier: Programming Language :: Python :: 3.10
Classifier: Programming Language :: Python :: 3.11
Classifier: Programming Language :: Python :: 3.12
Classifier: Programming Language :: Python :: 3.13
Requires-Python: >=3.10
License-File: LICENSE
Requires-Dist: numpy>=1.18.0
Requires-Dist: matplotlib>=3.1.0
Requires-Dist: scipy>=1.4.0
Requires-Dist: casadi>=3.5.0
Provides-Extra: dev
Requires-Dist: ruff>=0.1.0; extra == "dev"
Requires-Dist: mypy>=1.3.0; extra == "dev"
Requires-Dist: pytest>=7.0.0; extra == "dev"
Requires-Dist: pytest-cov>=4.0.0; extra == "dev"
Dynamic: license-file
